django_simple_forum/__init__.py
django_simple_forum/apps.py
django_simple_forum/facebook.py
django_simple_forum/forms.py
django_simple_forum/mixins.py
django_simple_forum/models.py
django_simple_forum/sending_mail.py
django_simple_forum/tests.py
django_simple_forum/urls.py
django_simple_forum/views.py
django_simple_forum/migrations/0001_initial.py
django_simple_forum/migrations/0002_auto_20160628_1211.py
django_simple_forum/migrations/0003_topic_tags.py
django_simple_forum/migrations/0004_topic_no_of_likes.py
django_simple_forum/migrations/0005_attachment.py
django_simple_forum/migrations/0006_forumcategory_description.py
django_simple_forum/migrations/0007_topic_no_of_votes.py
django_simple_forum/migrations/0008_auto_20160707_1311.py
django_simple_forum/migrations/0009_userprofile_profile_pic.py
django_simple_forum/migrations/0010_forumcategory_parent.py
django_simple_forum/migrations/0011_facebook_github_google_twitter.py
django_simple_forum/migrations/0012_comment_mentioned.py
django_simple_forum/migrations/0013_userprofile_send_mailnotifications.py
django_simple_forum/migrations/0014_auto_20170208_0550.py
django_simple_forum/migrations/__init__.py
django_simple_forum/static/css/bootstrap-suggest.css
django_simple_forum/static/css/dashboard.css
django_simple_forum/static/css/forum.css
django_simple_forum/static/css/jquery.tagsinput.css
django_simple_forum/static/css/login.css
django_simple_forum/static/css/ref.css
django_simple_forum/static/js/bootstrap-suggest.js
django_simple_forum/static/js/jquery.form.js
django_simple_forum/static/js/jquery.tagsinput.js
django_simple_forum/templates/login.html
django_simple_forum/templates/dashboard/badge_add.html
django_simple_forum/templates/dashboard/badges.html
django_simple_forum/templates/dashboard/categories.html
django_simple_forum/templates/dashboard/category_add.html
django_simple_forum/templates/dashboard/change_password.html
django_simple_forum-0.0.7.dist-info/DESCRIPTION.rst
django_simple_forum-0.0.7.dist-info/METADATA
django_simple_forum-0.0.7.dist-info/RECORD
django_simple_forum-0.0.7.dist-info/WHEEL
django_simple_forum-0.0.7.dist-info/metadata.json
django_simple_forum-0.0.7.dist-info/top_level.txt
